[
    {"name":"Buffet/Family", "img":"https://i.ibb.co/CB4n6bJ/buffet.jpg"},
    {"name":"Office Catering", "img":"https://i.ibb.co/56HsgbY/office-catering.jpg"},
    {"name":"Cultural Celebration", "img":"https://i.ibb.co/TK3hMrB/culturalcelebration.jpg"},
    {"name":"Plated", "img":"https://i.ibb.co/b1WQN5T/plated.jpg"},
    {"name":"BBQ", "img":"https://i.ibb.co/QMMkSDv/bbq.jpg"},
    {"name":"Sushi", "img":"https://i.ibb.co/J3R7730/sushi.jpg"},
    {"name":"Reception style", "img":"https://i.ibb.co/sbPXGZf/receptionstyle.jpg"},
    {"name":"Platters & prasentation", "img":"https://i.ibb.co/jfGLYwZ/platters.jpg"},
    {"name":"Beverages", "img":"https://i.ibb.co/hFRZ8Kd/Beverages.jpg"}
]